vcon/__init__.py
vcon/civic_address.py
vcon/dialog.py
vcon/extensions/__init__.py
vcon/extensions/base.py
vcon/extensions/lawful_basis/__init__.py
vcon/extensions/lawful_basis/attachment.py
vcon/extensions/lawful_basis/extension.py
vcon/extensions/lawful_basis/processing.py
vcon/extensions/lawful_basis/registry.py
vcon/extensions/lawful_basis/validation.py
vcon/extensions/registry.py
vcon/extensions/wtf/__init__.py
vcon/extensions/wtf/attachment.py
vcon/extensions/wtf/extension.py
vcon/extensions/wtf/processing.py
vcon/extensions/wtf/providers.py
vcon/extensions/wtf/validation.py
vcon/party.py
vcon/vcon.py
vcon-0.9.0.dist-info/LICENSE.txt
vcon-0.9.0.dist-info/METADATA
vcon-0.9.0.dist-info/WHEEL
vcon-0.9.0.dist-info/RECORD
