Metadata-Version: 2.3
Name: vcon
Version: 0.9.0
Summary: The vCon library - Complete vCon 0.3.0 specification implementation
License: MIT
Author: Thomas McCarthy-Howe
Author-email: ghostofbasho@gmail.com
Requires-Python: >=3.12,<4.0
Classifier: License :: OSI Approved :: MIT License
Classifier: Programming Language :: Python :: 3
Classifier: Programming Language :: Python :: 3.12
Classifier: Programming Language :: Python :: 3.13
Provides-Extra: image
Requires-Dist: authlib (>=1.6.4,<2.0.0)
Requires-Dist: ffmpeg (>=1.4,<2.0)
Requires-Dist: logger (>=1.4,<2.0)
Requires-Dist: mutagen (>=1.47.0,<2.0.0)
Requires-Dist: pillow (>=11.3.0,<12.0.0) ; extra == "image"
Requires-Dist: pydash (>=8.0.3,<9.0.0)
Requires-Dist: pypdf (>=6.0.0,<7.0.0) ; extra == "image"
Requires-Dist: python-dateutil (>=2.9.0.post0,<3.0.0)
Requires-Dist: requests (>=2.32.3,<3.0.0)
Requires-Dist: uuid6 (>=2024.7.10,<2025.0.0)
